acp_mcp/__init__.py
acp_mcp/adapter.py
acp_mcp-0.4.2.dist-info/METADATA
acp_mcp-0.4.2.dist-info/WHEEL
acp_mcp-0.4.2.dist-info/entry_points.txt
acp_mcp-0.4.2.dist-info/licenses/LICENSE
acp_mcp-0.4.2.dist-info/RECORD
