Metadata-Version: 2.4
Name: acp-mcp
Version: 0.4.2
Summary: Serve ACP agents over MCP
Author: IBM Corp.
Maintainer-email: Tomas Pilar <thomas7pilar@gmail.com>
License-Expression: Apache-2.0
License-File: LICENSE
Requires-Python: <4.0,>=3.11
Requires-Dist: acp-sdk>=0.8.4
Requires-Dist: mcp>=1.6.0
